test_example_package/__init__.py
test_example_package/example.py
test_example_package-0.0.2.data/data/requirements.txt
test_example_package-0.0.2.data/data/.git/config
test_example_package-0.0.2.dist-info/LICENSE
test_example_package-0.0.2.dist-info/METADATA
test_example_package-0.0.2.dist-info/WHEEL
test_example_package-0.0.2.dist-info/top_level.txt
test_example_package-0.0.2.dist-info/RECORD
