Metadata-Version: 2.1
Name: test-example-package
Version: 0.0.2
Summary: test_example_package: Test package to use it as template for building other packages
Home-page: https://github.com/R-Rijnbeek/test_example_package
Author: Robert Rijnbeek
Author-email: robert270384@gmail.com
License: UNKNOWN
Project-URL: Bug Tracker, https://github.com/R-Rijnbeek/test_example_package/issues
Platform: UNKNOWN
Classifier: Programming Language :: Python :: 3
Classifier: License :: OSI Approved :: MIT License
Classifier: Operating System :: OS Independent
Requires-Python: >=3.6
License-File: LICENSE
